std/__init__.py
std/cmp.py
std/marker.py
std/option.py
stdpy-0.0.1.dist-info/LICENSE
stdpy-0.0.1.dist-info/METADATA
stdpy-0.0.1.dist-info/WHEEL
stdpy-0.0.1.dist-info/top_level.txt
stdpy-0.0.1.dist-info/RECORD
