Metadata-Version: 2.1
Name: stdpy
Version: 0.0.1
Summary: std
Author: Rin Arakaki
License: MIT License
Project-URL: Repository, http://github.com/rnarkk/std.py
Classifier: Programming Language :: Python
Requires-Python: >=3.12
License-File: LICENSE
Provides-Extra: dev
Requires-Dist: pytest >=7.3.0 ; extra == 'dev'
